Metadata-Version: 2.1
Name: defshop_api
Version: 1.1.1
Summary: Defshop API
Author-email: sayginaego.say@gmail.com
